dedust_tonsdk/__init__.py
dedust_tonsdk/api.py
dedust_tonsdk/constants.py
dedust_tonsdk/contracts/__init__.py
dedust_tonsdk/contracts/dex/__init__.py
dedust_tonsdk/contracts/dex/common/__init__.py
dedust_tonsdk/contracts/dex/common/asset.py
dedust_tonsdk/contracts/dex/common/asset_error.py
dedust_tonsdk/contracts/dex/common/asset_type.py
dedust_tonsdk/contracts/dex/common/readiness_status.py
dedust_tonsdk/contracts/dex/factory/__init__.py
dedust_tonsdk/contracts/dex/factory/factory.py
dedust_tonsdk/contracts/dex/liquidity_deposit/__init__.py
dedust_tonsdk/contracts/dex/liquidity_deposit/liquidity_deposit.py
dedust_tonsdk/contracts/dex/pool/__init__.py
dedust_tonsdk/contracts/dex/pool/pool.py
dedust_tonsdk/contracts/dex/pool/pool_type.py
dedust_tonsdk/contracts/dex/vault/__init__.py
dedust_tonsdk/contracts/dex/vault/vault.py
dedust_tonsdk/contracts/dex/vault/vault_jetton.py
dedust_tonsdk/contracts/dex/vault/vault_native.py
dedust_tonsdk/contracts/jettons/__init__.py
dedust_tonsdk/contracts/jettons/jetton_root.py
dedust_tonsdk/contracts/jettons/jetton_wallet.py
dedust_tonsdk-1.0.5.dist-info/LICENSE.md
dedust_tonsdk-1.0.5.dist-info/WHEEL
dedust_tonsdk-1.0.5.dist-info/METADATA
dedust_tonsdk-1.0.5.dist-info/RECORD
