Metadata-Version: 2.1
Name: dedust-tonsdk
Version: 1.0.5
Summary: DeDust - DeDust SDK for Python.
Author: Shibdev, Dalvpv
Requires-Dist: httpx>=0.19.0
Requires-Dist: tonsdk>=1.0.13
